LICENSE
README.md
pyproject.toml
setup.py
ml_pentest.egg-info/PKG-INFO
ml_pentest.egg-info/SOURCES.txt
ml_pentest.egg-info/dependency_links.txt
ml_pentest.egg-info/top_level.txt
ml_pentest/attack_reports/__init__.py
ml_pentest/attack_reports/blackbox/__init__.py
ml_pentest/attack_reports/blackbox/genetic_attack/__init__.py
ml_pentest/attack_reports/blackbox/genetic_attack/GAMMA/__init__.py
ml_pentest/attack_reports/blackbox/genetic_attack/GAMMA/analize_results.py
ml_pentest/attacks/__init__.py
ml_pentest/attacks/blackbox/__init__.py
ml_pentest/attacks/blackbox/attack_result.py
ml_pentest/attacks/blackbox/blackbox_attack.py
ml_pentest/attacks/blackbox/genetic_attack/__init__.py
ml_pentest/attacks/blackbox/genetic_attack/GAMMA/__init__.py
ml_pentest/attacks/blackbox/genetic_attack/GAMMA/attack_utils.py
ml_pentest/attacks/blackbox/genetic_attack/GAMMA/gamma_api_call_injection.py
ml_pentest/attacks/blackbox/genetic_attack/GAMMA/gamma_attack.py
ml_pentest/attacks/blackbox/genetic_attack/GAMMA/gamma_result.py
ml_pentest/attacks/blackbox/genetic_attack/GAMMA/gamma_section_injection.py
ml_pentest/attacks/blackbox/genetic_attack/GAMMA/gamma_section_injection_ri.py
ml_pentest/attacks/blackbox/genetic_attack/GAMMA/gamma_section_injection_v2.py
ml_pentest/attacks/blackbox/genetic_attack/genetic_engine/__init__.py
ml_pentest/attacks/blackbox/genetic_attack/genetic_engine/genetic_algorithm_base.py
ml_pentest/file_manipulations/__init__.py
ml_pentest/file_manipulations/pe_format/__init__.py
ml_pentest/file_manipulations/pe_format/api_call_injection.py
ml_pentest/file_manipulations/pe_format/pe_manipulation.py
ml_pentest/file_manipulations/pe_format/section_injection.py
ml_pentest/file_manipulations/pe_format/section_injection_v2.py
ml_pentest/models/__init__.py
ml_pentest/models/dl_models/__init__.py
ml_pentest/models/dl_models/raw_bytes_based/LowMemConv.py
ml_pentest/models/dl_models/raw_bytes_based/__init__.py
ml_pentest/models/dl_models/raw_bytes_based/avastCNN.py
ml_pentest/models/dl_models/raw_bytes_based/malconv.py
ml_pentest/models/dl_models/raw_bytes_based/malconv2.py
