Metadata-Version: 2.1
Name: ml-pentest
Version: 0.0.1
Summary: Robustness evaluation framework for ML-Based Windows malware detectors
Home-page: https://github.com/gparrella12/ml_pentest
Author: gparrella
Classifier: Programming Language :: Python :: 3
Classifier: License :: OSI Approved :: GNU General Public License v3 (GPLv3)
Classifier: Operating System :: OS Independent
Requires-Python: >=3.8
License-File: LICENSE
